[
  {
    "id": 1,
    "subject": "sun",
    "question": "What type of star is the Sun?",
    "answerOptions": [
      { "choice": "Red Giant", "isCorrect": false },
      { "choice": "Red Dwarf", "isCorrect": false },
      { "choice": "White Dwarfs", "isCorrect": false },
      { "choice": "Yelllow Dwarf", "isCorrect": true }
    ]
  },
  {
    "id": 2,
    "subject": "sun",
    "question": "How old is our Sun (in billions of years)?",
    "answerOptions": [
      { "choice": "6", "isCorrect": false },
      { "choice": "4.5", "isCorrect": true },
      { "choice": "2", "isCorrect": false },
      { "choice": "3", "isCorrect": false }
    ]
  },
  {
    "id": 3,
    "subject": "sun",
    "question": "Helium is what percent of the makeup of the Sun?",
    "answerOptions": [
      { "choice": "7.8", "isCorrect": true },
      { "choice": "92.2", "isCorrect": false },
      { "choice": "86.5", "isCorrect": false },
      { "choice": "13.5", "isCorrect": false }
    ]
  },
  {
    "id": 4,
    "subject": "sun",
    "question": "What percent of our Solar System's mass does the Sun make up?",
    "answerOptions": [
      { "choice": "48.7", "isCorrect": false },
      { "choice": "99.8", "isCorrect": true },
      { "choice": "88", "isCorrect": false },
      { "choice": "50", "isCorrect": false }
    ]
  },
  {
    "id": 5,
    "subject": "sun",
    "question": "How hot is the Sun's core (in millions of degrees)?",
    "answerOptions": [
      { "choice": "100", "isCorrect": false },
      { "choice": "12", "isCorrect": false },
      { "choice": "44", "isCorrect": false },
      { "choice": "27", "isCorrect": true }
    ]
  },
  {
    "id": 6,
    "subject": "mercury",
    "question": "How many Earth days is one Mercury day?",
    "answerOptions": [
      { "choice": "59", "isCorrect": true },
      { "choice": "3", "isCorrect": false },
      { "choice": "Half", "isCorrect": false },
      { "choice": "12", "isCorrect": false }
    ]
  },
  {
    "id": 7,
    "subject": "mercury",
    "question": "How long does it take light to reach Mercury's surface (in minutes)?",
    "answerOptions": [
      { "choice": "1.5", "isCorrect": false },
      { "choice": "8", "isCorrect": false },
      { "choice": "2.7", "isCorrect": true },
      { "choice": "4.7", "isCorrect": false }
    ]
  },
  {
    "id": 8,
    "subject": "mercury",
    "question": "What's Mercury's highest recorded temperature (in Fahrenheit)?",
    "answerOptions": [
      { "choice": "2000", "isCorrect": false },
      { "choice": "800", "isCorrect": true },
      { "choice": "1550", "isCorrect": false },
      { "choice": "1200", "isCorrect": false }
    ]
  },
  {
    "id": 9,
    "subject": "mercury",
    "question": "What's Mercury's lowest recorded temperature (in Fahrenheit)?",
    "answerOptions": [
      { "choice": "-40", "isCorrect": false },
      { "choice": "-290", "isCorrect": true },
      { "choice": "32", "isCorrect": false },
      { "choice": "-400", "isCorrect": false }
    ]
  },
  {
    "id": 10,
    "subject": "mercury",
    "question": "How many moons does Mercury have?",
    "answerOptions": [
      { "choice": "1", "isCorrect": false },
      { "choice": "2", "isCorrect": false },
      { "choice": "3", "isCorrect": false },
      { "choice": "0", "isCorrect": true }
    ]
  },
  {
   "id":17,
   "subject":"earth",
  "question":"Earth is how many planets from the Sun?",
   "answerOptions":[
     {"choice":"Earth is 3rd","isCorrect": true},
     {"choice":"Earth is 1st","isCorrect": false},
     {"choice":"Earth is 5th","isCorrect": false},
     {"choice":"Earth is 4th","isCorrect": false}
  ]
},
{
   "id":18,
   "subject":"earth",
  "question":"How many moons does Earth have?",
  "answerOptions":[
     {"choice":"6","isCorrect": false},
     {"choice":"4","isCorrect": false},
     {"choice":"1","isCorrect": true},
     {"choice":"12","isCorrect": false}
  ]
},
{
   "id":19,
   "subject":"earth",
  "question":"How long is a day on Earth?",
  "answerOptions":[
     {"choice":"24 hours","isCorrect": true},
     {"choice":"23 hours","isCorrect": false},
     {"choice":"15 hours","isCorrect": false},
     {"choice":"33 hours","isCorrect": false}
  ]
},
{
   "id":20,
   "subject":"earth",
  "question":"How long is a revolution on Earth?",
   "answerOptions":[
     {"choice":"455 days","isCorrect": false},
     {"choice":"360 days","isCorrect": false},
     {"choice":"228 days","isCorrect": false},
     {"choice":"365 days","isCorrect": true}
  ]
},
{
   "id":21,
   "subject":"earth",
  "question":"What percent of Earth's atmosphere is Nitrogen?",
  "answerOptions":[
     {"choice":"78 Percent","isCorrect": true},
     {"choice":"21 Percent","isCorrect": false},
     {"choice":"1 Percent","isCorrect": false},
     {"choice":"44 Percent","isCorrect": false}
  ]
},
{
   "id":22,
   "subject":"earth",
  "question":"Approximately how long does it take light to reach Earth?",
  "answerOptions":[
     {"choice":"8.5 Minutes","isCorrect": true},
     {"choice":"15 Minutes","isCorrect": false},
     {"choice":"2 Minutes","isCorrect": false},
     {"choice":"12 Minutes","isCorrect": false}
  ]
},
{
   "id":23,
   "subject":"earth",
  "question":"What is Earth's distance from the sun (in million miles)?",
   "answerOptions":[
     {"choice":"22","isCorrect": false},
     {"choice":"400","isCorrect": false},
     {"choice":"57","isCorrect": false},
     {"choice":"94","isCorrect": true}
  ]
   } 
]
